{
"skeleton": { "hash": "TPb4jT4Cx9y9iAQi0SrPfnXCbe0", "spine": "2.1.27", "width": 767.62, "height": 1036.45, "images": "./stone_child/" },
"bones": [
	{ "name": "root" },
	{ "name": "Mask", "parent": "root", "x": -185.65, "y": 517.43 },
	{ "name": "leftArm", "parent": "root", "x": 160.02, "y": 618.13 },
	{ "name": "leftLeg", "parent": "root", "x": 126.18, "y": 238.37 },
	{ "name": "rightArm", "parent": "root", "x": -185.89, "y": 633.17 },
	{ "name": "rightLeg", "parent": "root", "x": -95.65, "y": 257.17 },
	{ "name": "bone", "parent": "leftLeg", "length": 203.07, "x": 3.76, "y": -18.79, "rotation": -89.09 },
	{ "name": "bone2", "parent": "rightLeg", "length": 219.82, "x": 3.75, "y": -15.04, "rotation": -102.43 },
	{ "name": "bone3", "parent": "leftArm", "length": 208.94, "x": 2.05, "y": -1.75, "rotation": 7.62 },
	{ "name": "bone4", "parent": "rightArm", "length": 130.26, "x": -2.17, "y": -6.06, "rotation": 167.03 }
],
"slots": [
	{ "name": "right_leg", "bone": "bone2", "attachment": "right_leg" },
	{ "name": "right_arm", "bone": "bone4", "attachment": "right_arm" },
	{ "name": "left_leg", "bone": "bone", "attachment": "left_leg" },
	{ "name": "Body", "bone": "root", "attachment": "Body" },
	{ "name": "Mask", "bone": "Mask", "attachment": "Mask" },
	{ "name": "left_arm", "bone": "bone3", "attachment": "left_arm" }
],
"skins": {
	"default": {
		"Body": {
			"Body": {
				"type": "mesh",
				"uvs": [ 0.1233, 0.03482, 0.0666, 0.12444, 0.01396, 0.24804, 0.01396, 0.36237, 0.02611, 0.54778, 0.02611, 0.68992, 0.02611, 0.81971, 0.11925, 0.92168, 0.22859, 0.97112, 0.31363, 1, 0.5323, 1, 0.78338, 0.98039, 0.88057, 0.93404, 0.9899, 0.8537, 0.99395, 0.70228, 0.96966, 0.57868, 0.90891, 0.40564, 0.87247, 0.24495, 0.83602, 0.12444, 0.76718, 0.08735, 0.66999, 0.07808, 0.53635, 0.04718, 0.43106, 0.01937, 0.29338, 8.3E-4, 0.17999, 0, 0.19619, 0.06572, 0.29743, 0.09354, 0.41487, 0.11826, 0.50396, 0.14298, 0.65379, 0.17079, 0.38652, 0.19242, 0.32578, 0.26658, 0.20024, 0.24186, 0.18809, 0.17388, 0.24883, 0.13371, 0.34602, 0.15225, 0.09495, 0.21096, 0.12735, 0.15225, 0.18809, 0.36546, 0.20024, 0.56941, 0.20834, 0.72392, 0.41082, 0.60958, 0.49181, 0.37473, 0.72668, 0.37782 ],
				"triangles": [ 25, 24, 23, 0, 24, 25, 26, 23, 22, 25, 23, 26, 27, 26, 22, 27, 22, 21, 34, 25, 26, 28, 27, 21, 35, 26, 27, 34, 26, 35, 37, 0, 25, 33, 37, 25, 1, 0, 37, 29, 21, 20, 28, 21, 29, 29, 20, 19, 29, 19, 18, 34, 33, 25, 30, 35, 27, 36, 1, 37, 32, 33, 34, 2, 1, 36, 31, 34, 35, 31, 35, 30, 32, 34, 31, 3, 2, 36, 36, 33, 32, 33, 36, 37, 38, 32, 31, 38, 36, 32, 3, 36, 38, 28, 30, 27, 42, 28, 29, 42, 30, 28, 31, 30, 42, 17, 43, 29, 17, 29, 18, 42, 29, 43, 43, 17, 16, 4, 3, 38, 38, 41, 39, 42, 38, 31, 4, 38, 39, 42, 41, 38, 5, 4, 39, 40, 39, 41, 5, 39, 40, 6, 5, 40, 41, 15, 11, 7, 6, 40, 43, 15, 41, 15, 43, 16, 13, 12, 14, 9, 8, 40, 7, 40, 8, 41, 42, 43, 11, 15, 14, 12, 11, 14, 41, 9, 40, 41, 10, 9, 11, 10, 41 ],
				"vertices": [ -216.14, 956.44, -255.03, 875.88, -291.15, 764.76, -291.15, 661.97, -282.81, 495.29, -282.81, 367.51, -282.81, 250.83, -218.92, 159.16, -143.91, 114.71, -85.58, 88.75, 64.43, 88.75, 236.66, 106.37, 303.33, 148.04, 378.34, 220.27, 381.12, 356.39, 364.45, 467.51, 322.78, 623.08, 297.78, 767.54, 272.78, 875.88, 225.55, 909.22, 158.88, 917.55, 67.19999, 945.33, -5.01, 970.33, -99.47, 987, -177.25, 987.75, -166.14, 928.66, -96.69, 903.66, -16.12999, 881.44, 44.98, 859.21, 147.77, 834.21, -35.57, 814.76, -77.24, 748.09, -163.36, 770.32, -171.69, 831.43, -130.02, 867.55, -63.35, 850.88, -235.59, 798.1, -213.36, 850.88, -171.69, 659.2, -163.36, 475.85, -157.8, 336.95, -18.9, 439.73, 36.65, 650.86, 197.77, 648.08 ],
				"hull": 25,
				"edges": [ 0, 2, 2, 4, 4, 6, 6, 8, 8, 10, 10, 12, 12, 14, 14, 16, 16, 18, 18, 20, 20, 22, 22, 24, 24, 26, 26, 28, 28, 30, 30, 32, 32, 34, 34, 36, 36, 38, 38, 40, 40, 42, 42, 44, 44, 46, 46, 48, 0, 48, 0, 50, 50, 52, 52, 54, 54, 56, 56, 58, 36, 58, 70, 60, 60, 62, 62, 64, 64, 66, 66, 68, 68, 70, 2, 74, 74, 72, 72, 4 ],
				"width": 686,
				"height": 899
			}
		},
		"Mask": {
			"Mask": { "x": -25.77, "y": 24.73, "width": 201, "height": 500 }
		},
		"left_arm": {
			"left_arm": { "x": 112.05, "y": -0.36, "rotation": -7.62, "width": 322, "height": 234 }
		},
		"left_leg": {
			"left_leg": { "x": 131.34, "y": 3.36, "rotation": 89.09, "width": 270, "height": 274 }
		},
		"right_arm": {
			"right_arm": { "x": 85.86, "y": -10.61, "rotation": -167.03, "width": 128, "height": 155 }
		},
		"right_leg": {
			"right_leg": { "x": 117.21, "y": 2.78, "rotation": 102.43, "width": 199, "height": 281 }
		}
	}
},
"animations": {
	"Attack": {
		"bones": {
			"root": {
				"rotate": [
					{ "time": 0, "angle": 0 },
					{ "time": 0.4333, "angle": -25.89, "curve": "stepped" },
					{ "time": 1.0666, "angle": -25.89 },
					{ "time": 1.3, "angle": 11.2 },
					{ "time": 1.9666, "angle": 0 }
				],
				"translate": [
					{ "time": 0.4333, "x": 0, "y": 0 },
					{ "time": 1.0666, "x": 82.64, "y": 0 },
					{ "time": 1.3, "x": -86.85, "y": 0 },
					{ "time": 1.9666, "x": 0, "y": 0 }
				]
			},
			"bone4": {
				"rotate": [
					{ "time": 0, "angle": 0 },
					{ "time": 0.7666, "angle": -37.82, "curve": "stepped" },
					{ "time": 1.0666, "angle": -37.82 },
					{ "time": 1.3, "angle": -335.68 },
					{ "time": 1.9666, "angle": 0 }
				],
				"translate": [
					{ "time": 0, "x": 0, "y": 0, "curve": "stepped" },
					{ "time": 1.0666, "x": 0, "y": 0 },
					{ "time": 1.3, "x": -44.86, "y": -24.17 },
					{ "time": 1.9666, "x": 0, "y": 0 }
				]
			},
			"bone3": {
				"rotate": [
					{ "time": 0, "angle": 0 },
					{ "time": 0.7666, "angle": 42.07, "curve": "stepped" },
					{ "time": 1.0666, "angle": 42.07 },
					{ "time": 1.3, "angle": -144.97 },
					{ "time": 1.7333, "angle": 114.12 },
					{ "time": 1.9666, "angle": 0 }
				]
			},
			"bone": {
				"rotate": [
					{ "time": 0, "angle": 0 },
					{ "time": 0.4333, "angle": 35.49 },
					{ "time": 1, "angle": 9.61 },
					{ "time": 1.3, "angle": 22.92 },
					{ "time": 1.9666, "angle": 0 }
				],
				"translate": [
					{ "time": 0, "x": 0, "y": 0 },
					{ "time": 0.4333, "x": -41.27, "y": 56 },
					{ "time": 1, "x": -29.92, "y": 56.3 },
					{ "time": 1.3, "x": -15.6, "y": 0.66 },
					{ "time": 1.9666, "x": 0, "y": 0 }
				]
			},
			"bone2": {
				"rotate": [
					{ "time": 0, "angle": 0 },
					{ "time": 0.2666, "angle": 27.73 },
					{ "time": 0.7666, "angle": 23.59 },
					{ "time": 1.0333, "angle": 13.03 },
					{ "time": 1.3, "angle": -40.38 },
					{ "time": 1.6666, "angle": 6.41 },
					{ "time": 1.9666, "angle": 0 }
				],
				"translate": [
					{ "time": 0, "x": 0, "y": 0 },
					{ "time": 0.7666, "x": 8.01, "y": -16.52 },
					{ "time": 1.0333, "x": 8.15, "y": -29.79 },
					{ "time": 1.3, "x": 38.56, "y": -17.8 },
					{ "time": 1.6666, "x": 40.11, "y": -0.2 },
					{ "time": 1.9666, "x": 0, "y": 0 }
				]
			},
			"Mask": {
				"rotate": [
					{ "time": 0, "angle": 0, "curve": "stepped" },
					{ "time": 1.0666, "angle": 0 },
					{ "time": 1.3, "angle": 9.9 },
					{ "time": 1.4333, "angle": -6.88 },
					{ "time": 1.6666, "angle": 0 }
				],
				"translate": [
					{ "time": 0, "x": 0, "y": 0, "curve": "stepped" },
					{ "time": 1.0666, "x": 0, "y": 0 },
					{ "time": 1.3, "x": 0, "y": 14.86 },
					{ "time": 1.4333, "x": 0, "y": -5.03 },
					{ "time": 1.6666, "x": 0, "y": 0 }
				]
			}
		},
		"ffd": {
			"default": {
				"Body": {
					"Body": [
						{ "time": 0 },
						{
							"time": 1.0666,
							"offset": 3,
							"vertices": [ -9.2071, -3.0E-5, 10.19504, 0, 0, 0, 0, 0, 0, 0, 0, 0, 0, 0, 0, 0, 0, 0, 0, 0, 0, 0, 0, 0, 0, 0, 0, 0, 0, 0, 0, 0, 0, 0, 0, 0, 0, 0, 0, 0, 0, 0, 0, 0, 0, 0, 0, 0, 0, 0, 0, 0, 0, 0, 0, 0, 0, -4.0E-5, -2.14525, -1.2E-4, 21.55306, -6.0E-5, 13.65363, -6.0E-5, -8.06975, -1.0E-4, -20.9064, -1.6E-4, -14.98184, -2.0E-5, 4.37438, -7.0E-5, -4.84162 ]
						},
						{
							"time": 1.3,
							"offset": 1,
							"vertices": [ 19.22669, -0.51678, 18.06655, -5.57156, -20.00476, 0, 0, 0, 0, 0, 0, 0, 0, 0, 0, 0, 0, 0, 0, 0, 0, 0, 0, 0, 0, 0, 0, 0, 0, 0, 0, 0, 0, 0, 0, 2.0E-5, 19.22669, 0, 0, 0, 0, 0, 0, 0, 0, 0, 0, 0, 0, 2.0E-5, 19.22669, 2.0E-5, 19.22669, 2.0E-5, 19.22669, 2.0E-5, 19.22669, 2.0E-5, 19.22669, 18.5445, 0.85853, 7.76945, -8.62386, -14.49868, -5.4631, -16.65361, 3.2292, -5.87873, 8.3654, 11.36107, 5.99479, 2.20509, -8.58323, 5.31578, 9.50056 ]
						},
						{
							"time": 1.4666,
							"offset": 1,
							"vertices": [ 9.15265, 0, 0, 0, 0, 0, 0, 0, 0, 0, 0, 0, 0, 0, 0, 0, 0, 0, 0, 0, 0, 0, 0, 0, 0, 0, 0, 0, 0, 0, 0, 0, 0, 0, 0, -3.0E-5, 9.15265, 0, 0, 0, 0, 0, 0, 0, 0, 0, 0, 0, 0, -3.0E-5, 9.15265, -3.0E-5, 9.15265, -3.0E-5, 9.15265, -3.0E-5, 9.15265, -3.0E-5, 9.15265 ]
						},
						{ "time": 1.9666 }
					]
				}
			}
		}
	},
	"Idle": {
		"bones": {
			"root": {
				"rotate": [
					{ "time": 0, "angle": 0 },
					{ "time": 0.5, "angle": 359 },
					{ "time": 1.5, "angle": 1 },
					{ "time": 1.9666, "angle": 0 }
				],
				"scale": [
					{ "time": 0, "x": 1, "y": 1, "curve": "stepped" },
					{ "time": 0.6666, "x": 1, "y": 1, "curve": "stepped" },
					{ "time": 1.9666, "x": 1, "y": 1 }
				]
			},
			"Mask": {
				"rotate": [
					{ "time": 0, "angle": 0 },
					{ "time": 0.7, "angle": -2.34 },
					{ "time": 1.1666, "angle": -3.84 },
					{ "time": 1.9666, "angle": 0 }
				]
			},
			"bone3": {
				"rotate": [
					{ "time": 0, "angle": 0 },
					{ "time": 0.8333, "angle": -12.19 },
					{ "time": 1.9666, "angle": 0 }
				]
			},
			"bone4": {
				"rotate": [
					{ "time": 0, "angle": 0 },
					{ "time": 1.2666, "angle": -14.25 },
					{ "time": 1.9666, "angle": 0 }
				]
			},
			"bone2": {
				"translate": [
					{ "time": 0, "x": 0, "y": 0 },
					{ "time": 0.6666, "x": -0.81, "y": -3.69 },
					{ "time": 1.9666, "x": 0, "y": 0 }
				]
			},
			"bone": {
				"translate": [
					{ "time": 0, "x": 0, "y": 0 },
					{ "time": 1.1, "x": 0.15, "y": 3.88 },
					{ "time": 1.9666, "x": 0, "y": 0 }
				]
			}
		},
		"ffd": {
			"default": {
				"Body": {
					"Body": [
						{ "time": 1.3 },
						{
							"time": 1.4,
							"offset": 2,
							"vertices": [ -0.50021, -7.14593, -5.39437, 7.91302, 0, 0, 0, 0, 0, 0, 0, 0, 0, 0, 0, 0, 0, 0, 0, 0, 0, 0, 0, 0, 0, 0, 0, 0, 0, 0, 0, 0, 0, 0, 0, 0, 0, 0, 0, 0, 0, 0, 0, 0, 0, 0, 0, 0, 0, 0, 0, 0, 0, 0, 0, 0, 0, 0, 15.27296, -1.98638, 6.39891, 19.9566, -11.94085, 12.64233, -13.71566, -7.47216, -4.84159, -19.35797, 9.35692, -13.87219, 2.13511, 3.39532, 5.14691, -3.75769 ]
						},
						{ "time": 1.5 }
					]
				}
			}
		}
	},
	"Walk": {
		"bones": {
			"bone2": {
				"rotate": [
					{ "time": 0, "angle": 0 },
					{ "time": 0.3333, "angle": -18.92 },
					{ "time": 0.7666, "angle": -20.46 },
					{ "time": 1.2333, "angle": 14.19 },
					{ "time": 1.7, "angle": 43.5 },
					{ "time": 1.9666, "angle": 0 }
				],
				"translate": [
					{ "time": 0, "x": 0, "y": 0 },
					{ "time": 0.3333, "x": 11.3, "y": 56.51 },
					{ "time": 0.7666, "x": -45.21, "y": -16.95 },
					{ "time": 1.2333, "x": -11.3, "y": -16.95 },
					{ "time": 1.7, "x": -11.3, "y": 16.95 },
					{ "time": 1.9666, "x": 0, "y": 0 }
				],
				"scale": [
					{ "time": 0, "x": 1, "y": 1, "curve": "stepped" },
					{ "time": 1.9666, "x": 1, "y": 1 }
				]
			},
			"bone": {
				"rotate": [
					{ "time": 0, "angle": 0 },
					{ "time": 0.3333, "angle": 26.88 },
					{ "time": 0.7666, "angle": 38.39 },
					{ "time": 1.2333, "angle": -13.17 },
					{ "time": 1.7, "angle": -30.3 },
					{ "time": 1.9666, "angle": 0 }
				],
				"translate": [
					{ "time": 0, "x": 0, "y": 0 },
					{ "time": 0.3333, "x": 5.65, "y": 11.3 },
					{ "time": 0.7666, "x": 5.65, "y": 50.86 },
					{ "time": 1.2333, "x": 5.65, "y": 33.91 },
					{ "time": 1.7, "x": -45.21, "y": -22.6 },
					{ "time": 1.9666, "x": 0, "y": 0 }
				],
				"scale": [
					{ "time": 0, "x": 1, "y": 1, "curve": "stepped" },
					{ "time": 1.9666, "x": 1, "y": 1 }
				]
			},
			"bone3": {
				"rotate": [
					{ "time": 0, "angle": 0 },
					{ "time": 0.4333, "angle": -24.88 },
					{ "time": 0.7333, "angle": 11.78 },
					{ "time": 1, "angle": 0 }
				],
				"scale": [
					{ "time": 0, "x": 1, "y": 1 },
					{ "time": 0.4666, "x": 0.95, "y": 0.95 },
					{ "time": 0.9666, "x": 1, "y": 1 },
					{ "time": 1.4666, "x": 1.05, "y": 1.05 },
					{ "time": 1.9666, "x": 1, "y": 1 }
				]
			},
			"bone4": {
				"rotate": [
					{ "time": 0, "angle": 0 },
					{ "time": 0.5, "angle": -12.89 },
					{ "time": 0.7666, "angle": -321.19 },
					{ "time": 1.2333, "angle": -10.55 },
					{ "time": 1.5, "angle": 2.24 },
					{ "time": 1.9666, "angle": 0 }
				],
				"translate": [
					{ "time": 0, "x": 0, "y": 0 },
					{ "time": 0.5, "x": -45.21, "y": 0 },
					{ "time": 0.7666, "x": -22.6, "y": -5.65 },
					{ "time": 1.2333, "x": -5.65, "y": -5.65 },
					{ "time": 1.5, "x": 5.65, "y": -11.3 }
				]
			},
			"Mask": {
				"rotate": [
					{ "time": 0, "angle": 0 },
					{ "time": 1.0333, "angle": -2.97 },
					{ "time": 1.2333, "angle": -0.63 },
					{ "time": 1.7, "angle": 0 }
				],
				"translate": [
					{ "time": 0, "x": 0, "y": 0 },
					{ "time": 0.7666, "x": 0, "y": 13.05 },
					{ "time": 1.0333, "x": 0, "y": 3.26 },
					{ "time": 1.2333, "x": 0, "y": 6.52 },
					{ "time": 1.7, "x": 0, "y": 0 }
				]
			},
			"root": {
				"rotate": [
					{ "time": 0, "angle": 0 },
					{ "time": 0.4666, "angle": -4.27 },
					{ "time": 0.9666, "angle": 0, "curve": "stepped" },
					{ "time": 1.0333, "angle": 0 },
					{ "time": 1.4666, "angle": 6.29 },
					{ "time": 1.9666, "angle": 0 }
				]
			}
		},
		"ffd": {
			"default": {
				"Body": {
					"Body": [
						{ "time": 0 },
						{
							"time": 0.4666,
							"vertices": [ 4.85943, -22.49475, 5.63726, 0.05358, 6.35955, -12.89062, 6.35955, -2.86535, 6.19287, 0.46823, 6.19287, 3.02398, 6.19287, 5.35752, 4.91497, 7.19097, 3.41485, 8.07992, 2.24811, 8.59902, -0.75212, 8.59902, -4.19683, 8.2466, -5.53027, 7.4132, -7.03039, 5.96865, -7.08593, 3.24621, -6.75259, 1.02383, -5.91918, -2.08752, -5.41915, -4.97668, -4.91912, -20.88354, -3.9746, -7.81018, -2.64117, -7.97686, -0.80767, -8.53247, 0.63688, -9.03253, 2.52591, -9.3659, 4.08157, -9.38092, 3.85934, -21.93914, 2.47035, -21.43914, 0.85912, -20.99469, -0.3632, -20.55017, -2.41891, -20.05011, 6.99998, -5.43713, 4.49132, -9.45098, -0.69323, -8.11303, -1.19499, -4.43365, 1.3137, -2.25952, 5.32755, -3.26293, 5.24833, -9.00726, 4.80387, -2.85882, 3.97047, -2.80981, 3.80378, 0.85714, 3.69267, 3.63516, 19.61167, 1.5794, -0.19651, -2.64312, -3.41899, -2.58758 ]
						},
						{ "time": 0.9666 },
						{
							"time": 1.4666,
							"vertices": [ -7.21847, 13.0617, -8.1763, 10.64477, -7.21533, 7.31121, -9.46862, 4.22766, -9.21862, -0.77276, -9.21862, -4.60638, -9.21862, -5.27618, -7.30181, -8.02639, -5.05163, -9.35983, -3.30149, -10.13849, 1.19886, -10.13849, 6.36593, -12.44034, -2.95571, -11.19024, -0.70553, -9.0234, -0.62216, -4.93975, 10.19958, -1.60614, 8.94946, 3.06085, 8.1994, 7.39453, 7.44937, 10.64477, 6.03259, 11.64489, 4.0324, 11.89489, 1.28219, 12.72827, -0.88463, 13.47839, -3.71819, 13.97845, -6.05172, 14.00097, -5.71835, 12.22827, -3.63484, 11.47821, -1.218, 10.81152, 0.61548, 10.14477, 3.69906, 9.39471, -16.00334, 8.81134, -9.00167, 6.81115, 5.4685, 7.4779, 6.86882, 9.3114, -0.13284, 10.39477, -11.33555, 9.89471, -8.69372, 8.31127, -9.28508, 9.89471, -5.88502, 4.14428, -5.63502, -1.35614, -5.46833, -5.52313, -1.30134, -19.42218, 0.36545, 3.89428, 5.1992, 3.81091 ]
						},
						{ "time": 1.9666 }
					]
				}
			}
		}
	}
}
}